lcn_frontend/__init__.py
lcn_frontend/constants.py
lcn_frontend/entrypoint.822ba5cabf4f2b2b.js
lcn_frontend/entrypoint.822ba5cabf4f2b2b.js.br
lcn_frontend/py.typed
lcn_frontend/frontend_es5/117.9787836bb7f2387b.js
lcn_frontend/frontend_es5/117.9787836bb7f2387b.js.LICENSE.txt
lcn_frontend/frontend_es5/117.9787836bb7f2387b.js.br
lcn_frontend/frontend_es5/117.9787836bb7f2387b.js.map
lcn_frontend/frontend_es5/143.3ed99e72ef75b90e.js
lcn_frontend/frontend_es5/143.3ed99e72ef75b90e.js.LICENSE.txt
lcn_frontend/frontend_es5/143.3ed99e72ef75b90e.js.br
lcn_frontend/frontend_es5/143.3ed99e72ef75b90e.js.map
lcn_frontend/frontend_es5/15.b8d63e2cbb81a2af.js
lcn_frontend/frontend_es5/15.b8d63e2cbb81a2af.js.br
lcn_frontend/frontend_es5/15.b8d63e2cbb81a2af.js.map
lcn_frontend/frontend_es5/163.bd00fa5818a6cc80.js
lcn_frontend/frontend_es5/163.bd00fa5818a6cc80.js.LICENSE.txt
lcn_frontend/frontend_es5/163.bd00fa5818a6cc80.js.br
lcn_frontend/frontend_es5/163.bd00fa5818a6cc80.js.map
lcn_frontend/frontend_es5/175.61f0e924f21c2841.js
lcn_frontend/frontend_es5/175.61f0e924f21c2841.js.br
lcn_frontend/frontend_es5/175.61f0e924f21c2841.js.map
lcn_frontend/frontend_es5/28.f2701cff3fd937b9.js
lcn_frontend/frontend_es5/28.f2701cff3fd937b9.js.LICENSE.txt
lcn_frontend/frontend_es5/28.f2701cff3fd937b9.js.br
lcn_frontend/frontend_es5/28.f2701cff3fd937b9.js.map
lcn_frontend/frontend_es5/297.d699567ea4e84f8c.js
lcn_frontend/frontend_es5/297.d699567ea4e84f8c.js.br
lcn_frontend/frontend_es5/297.d699567ea4e84f8c.js.map
lcn_frontend/frontend_es5/314.d514b54516a1f254.js
lcn_frontend/frontend_es5/314.d514b54516a1f254.js.br
lcn_frontend/frontend_es5/314.d514b54516a1f254.js.map
lcn_frontend/frontend_es5/453.2aad7b0f6fd21ccd.js
lcn_frontend/frontend_es5/453.2aad7b0f6fd21ccd.js.LICENSE.txt
lcn_frontend/frontend_es5/453.2aad7b0f6fd21ccd.js.br
lcn_frontend/frontend_es5/453.2aad7b0f6fd21ccd.js.map
lcn_frontend/frontend_es5/466.cbd27ad39a0f53a5.js
lcn_frontend/frontend_es5/466.cbd27ad39a0f53a5.js.br
lcn_frontend-0.2.8.dist-info/licenses/LICENSE
lcn_frontend-0.2.8.dist-info/METADATA
lcn_frontend-0.2.8.dist-info/WHEEL
lcn_frontend-0.2.8.dist-info/top_level.txt
lcn_frontend-0.2.8.dist-info/RECORD
