Metadata-Version: 2.4
Name: lcn_frontend
Version: 0.2.8
Summary: LCN panel for Home Assistant
Author-email: Andre Lengwenus <alengwenus@gmail.com>
License: MIT
Project-URL: Repository, https://github.com/alengwenus/lcn-frontend.git
Keywords: Home Assistant,LCN
Requires-Python: >=3.11.0
License-File: LICENSE
Dynamic: license-file
